.hgignore
.hgtags
CHANGES.txt
LICENSE.txt
MANIFEST.in
README.txt
bootstrap.py
buildout.cfg
setup.py
js/__init__.py
js.mochikit.egg-info/PKG-INFO
js.mochikit.egg-info/SOURCES.txt
js.mochikit.egg-info/dependency_links.txt
js.mochikit.egg-info/entry_points.txt
js.mochikit.egg-info/namespace_packages.txt
js.mochikit.egg-info/not-zip-safe
js.mochikit.egg-info/requires.txt
js.mochikit.egg-info/top_level.txt
js/mochikit/__init__.py
js/mochikit/test_mochikit.txt
js/mochikit/resources/Async.js
js/mochikit/resources/Async.min.js
js/mochikit/resources/Base.js
js/mochikit/resources/Base.min.js
js/mochikit/resources/Color.js
js/mochikit/resources/Color.min.js
js/mochikit/resources/DOM.js
js/mochikit/resources/DOM.min.js
js/mochikit/resources/DateTime.js
js/mochikit/resources/DateTime.min.js
js/mochikit/resources/DragAndDrop.js
js/mochikit/resources/DragAndDrop.min.js
js/mochikit/resources/Format.js
js/mochikit/resources/Format.min.js
js/mochikit/resources/Iter.js
js/mochikit/resources/Iter.min.js
js/mochikit/resources/Logging.js
js/mochikit/resources/Logging.min.js
js/mochikit/resources/LoggingPane.js
js/mochikit/resources/LoggingPane.min.js
js/mochikit/resources/MochiKit.js
js/mochikit/resources/MochiKit.min.js
js/mochikit/resources/MockDOM.js
js/mochikit/resources/MockDOM.min.js
js/mochikit/resources/Position.js
js/mochikit/resources/Position.min.js
js/mochikit/resources/README.txt
js/mochikit/resources/Selector.js
js/mochikit/resources/Selector.min.js
js/mochikit/resources/Signal.js
js/mochikit/resources/Signal.min.js
js/mochikit/resources/Sortable.js
js/mochikit/resources/Sortable.min.js
js/mochikit/resources/Style.js
js/mochikit/resources/Style.min.js
js/mochikit/resources/Test.js
js/mochikit/resources/Test.min.js
js/mochikit/resources/Visual.js
js/mochikit/resources/Visual.min.js