Metadata-Version: 1.0
Name: js.mochikit
Version: 1.4.2-1
Summary: Fanstatic packaging of Mochikit
Home-page: https://bitbucket.org/gocept/js.mochikit
Author: gocept Developers
Author-email: mail@gocept.com
License: BSD
Platform: UNKNOWN
